{"title": "Clarkesworld Magazine - Science Fiction & Fantasy", "author": "JC Jongwon Park", "hostname": "clarkesworldmagazine.com", "date": "2022-01-01", "categories": "", "tags": "", "fingerprint": "kJxcJUWYaK2XAyEZdZ37Lw92Om8=", "id": null, "license": null, "comments": "", "raw_text": "Cover Art  GUYS! Don't Lose Hope    JC Jongwon Park is an illustrator and concept artist based in Hamburg, Germany where he currently works in the video game, feature film, animation, TV commercial, and publishing industries. JC has created concept art for games such as Gears of War, Chorus, Everspace, Aion, and Legend of the Cryptids.", "text": "Cover Art\nGUYS! Don't Lose Hope\nJC Jongwon Park is an illustrator and concept artist based in Hamburg, Germany where he currently works in the video game, feature film, animation, TV commercial, and publishing industries. JC has created concept art for games such as Gears of War, Chorus, Everspace, Aion, and Legend of the Cryptids.", "source": "https://clarkesworldmagazine.com/artbio_175/", "source-hostname": "Clarkesworld Magazine", "excerpt": "Clarkesworld Science Fiction and Fantasy Magazine and Podcast. This page: GUYS! Don't Lose Hope by JC Jongwon Park"}